naver_articrawler/__init__.py
naver_articrawler/newsCrawler.py
naver_articrawler-0.1.3.dist-info/LICENSE
naver_articrawler-0.1.3.dist-info/METADATA
naver_articrawler-0.1.3.dist-info/WHEEL
naver_articrawler-0.1.3.dist-info/top_level.txt
naver_articrawler-0.1.3.dist-info/RECORD
